[
  {
    "scope": "https://api.github.com:443",
    "method": "get",
    "path": "/orgs/octokit-fixture-org",
    "body": "",
    "status": 200,
    "response": {
      "login": "octokit-fixture-org",
      "id": 31898100,
      "node_id": "MDEyOk9yZ2FuaXphdGlvbjMxODk4MTAw",
      "url": "https://api.github.com/orgs/octokit-fixture-org",
      "repos_url": "https://api.github.com/orgs/octokit-fixture-org/repos",
      "events_url": "https://api.github.com/orgs/octokit-fixture-org/events",
      "hooks_url": "https://api.github.com/orgs/octokit-fixture-org/hooks",
      "issues_url": "https://api.github.com/orgs/octokit-fixture-org/issues",
      "members_url": "https://api.github.com/orgs/octokit-fixture-org/members{/member}",
      "public_members_url": "https://api.github.com/orgs/octokit-fixture-org/public_members{/member}",
      "avatar_url": "https://avatars2.githubusercontent.com/u/31898100?v=4",
      "description": null,
      "has_organization_projects": true,
      "has_repository_projects": true,
      "public_repos": 28,
      "public_gists": 0,
      "followers": 0,
      "following": 0,
      "html_url": "https://github.com/octokit-fixture-org",
      "created_at": "2017-09-12T16:55:36Z",
      "updated_at": "2018-06-13T04:29:26Z",
      "type": "Organization"
    },
    "rawHeaders": [
      "Date",
      "Thu, 12 Jul 2018 05:59:10 GMT",
      "Content-Type",
      "application/json; charset=utf-8",
      "Transfer-Encoding",
      "chunked",
      "Connection",
      "close",
      "Set-Cookie",
      "__cfduid=d5edf3b3ccb8d52c036988ba8bf53d8a41531375150; expires=Fri, 12-Jul-19 05:59:10 GMT; path=/; domain=.octokit-fixtures-proxy.now.sh; HttpOnly",
      "status",
      "200 OK",
      "x-ratelimit-limit",
      "60",
      "x-ratelimit-remaining",
      "59",
      "x-ratelimit-reset",
      "1531378750",
      "cache-control",
      "public, max-age=60, s-maxage=60",
      "vary",
      "Accept, Accept-Encoding",
      "etag",
      "W/\"caa2c48fe3cc3d1b1ee2538b423e8f75\"",
      "last-modified",
      "Wed, 13 Jun 2018 04:29:26 GMT",
      "x-github-media-type",
      "github.v3; format=json",
      "access-control-expose-headers",
      "ETag, Link, Retry-After, X-GitHub-OTP, X-RateLimit-Limit, X-RateLimit-Remaining, X-RateLimit-Reset, X-OAuth-Scopes, X-Accepted-OAuth-Scopes, X-Poll-Interval",
      "access-control-allow-origin",
      "*",
      "strict-transport-security",
      "max-age=31536000; includeSubdomains; preload",
      "x-frame-options",
      "deny",
      "x-content-type-options",
      "nosniff",
      "x-xss-protection",
      "1; mode=block",
      "referrer-policy",
      "origin-when-cross-origin, strict-origin-when-cross-origin",
      "content-security-policy",
      "default-src 'none'",
      "x-runtime-rack",
      "0.041163",
      "x-github-request-id",
      "DFAE:9C3C:65480AE:8C8684C:5B46EE2E",
      "x-now-trace",
      "sfo1",
      "now",
      "1",
      "X-Now-Id",
      "3v2wf-1531375150380-UwYxrvVJSXcOe4gyZ0qTf5oi",
      "X-Now-Instance",
      "2674252314",
      "CF-Cache-Status",
      "EXPIRED",
      "Expect-CT",
      "max-age=604800, report-uri=\"https://report-uri.cloudflare.com/cdn-cgi/beacon/expect-ct\"",
      "Server",
      "cloudflare",
      "CF-RAY",
      "439148403bd54716-EWR"
    ],
    "reqheaders": {
      "accept": "application/vnd.github.v3+json",
      "host": "api.github.com"
    }
  }
]
